{
  "_note1": "KEEP THIS FILE! Check it into a version control system (VCS) like git.",
  "_note2": "ObjectBox manages crucial IDs for your object model. See docs for details.",
  "_note3": "If you have VCS merge conflicts, you must resolve them according to ObjectBox docs.",
  "entities": [
    {
      "id": "1:1538093140391081267",
      "lastPropertyId": "8:2927502878137602904",
      "name": "App",
      "properties": [
        {
          "id": "1:6515470921698593162",
          "name": "_id",
          "type": 6,
          "flags": 3
        },
        {
          "id": "2:1635119710587285181",
          "name": "id",
          "type": 9
        },
        {
          "id": "3:537063216129484593",
          "name": "name",
          "type": 9
        },
        {
          "id": "4:673451063985783355",
          "name": "version",
          "type": 9
        },
        {
          "id": "5:5857546976442964303",
          "name": "downloads",
          "type": 5,
          "flags": 4
        },
        {
          "id": "6:8614175798517797650",
          "name": "launchDate",
          "type": 9
        },
        {
          "id": "7:6233099137678283459",
          "name": "rating",
          "type": 8,
          "flags": 4
        },
        {
          "id": "8:2927502878137602904",
          "name": "icon",
          "type": 9
        }
      ],
      "relations": []
    }
  ],
  "lastEntityId": "1:1538093140391081267",
  "lastIndexId": "0:0",
  "lastRelationId": "0:0",
  "lastSequenceId": "0:0",
  "modelVersion": 5,
  "modelVersionParserMinimum": 5,
  "retiredEntityUids": [],
  "retiredIndexUids": [],
  "retiredPropertyUids": [],
  "retiredRelationUids": [],
  "version": 1
}